{
  "taiwan_cement": {
    "earliest": "2021-11-16",
    "latest": "2026-04-24",
    "count": 1073
  },
  "asia_cement": {
    "earliest": "2021-11-16",
    "latest": "2026-04-24",
    "count": 1073
  },
  "taiwan_glass": {
    "earliest": "2021-11-16",
    "latest": "2026-04-24",
    "count": 1073
  },
  "tung_ho_steel": {
    "earliest": "2021-11-16",
    "latest": "2026-04-24",
    "count": 1073
  },
  "nippon_steel": {
    "earliest": "2021-11-17",
    "latest": "2026-04-24",
    "count": 1085
  },
  "crh": {
    "earliest": "2021-11-12",
    "latest": "2026-04-24",
    "count": 1115
  },
  "vulcan_materials": {
    "earliest": "2021-11-12",
    "latest": "2026-04-24",
    "count": 1115
  },
  "caterpillar": {
    "earliest": "2021-11-12",
    "latest": "2026-04-24",
    "count": 1115
  },
  "saint_gobain": {
    "earliest": "2021-11-15",
    "latest": "2026-04-24",
    "count": 1137
  },
  "cathay_real_estate": {
    "earliest": "2021-11-16",
    "latest": "2026-04-24",
    "count": 1073
  },
  "huaku": {
    "earliest": "2021-11-16",
    "latest": "2026-04-24",
    "count": 1073
  },
  "chong_hong": {
    "earliest": "2021-11-16",
    "latest": "2026-04-24",
    "count": 1073
  },
  "highwealth": {
    "earliest": "2021-11-16",
    "latest": "2026-04-24",
    "count": 1073
  },
  "ruentex": {
    "earliest": "2021-11-16",
    "latest": "2026-04-24",
    "count": 1073
  },
  "kindom": {
    "earliest": "2021-11-16",
    "latest": "2026-04-24",
    "count": 1073
  },
  "farglory": {
    "earliest": "2021-11-16",
    "latest": "2026-04-24",
    "count": 1073
  },
  "huang_hsiang": {
    "earliest": "2021-11-16",
    "latest": "2026-04-24",
    "count": 1073
  },
  "dr_horton": {
    "earliest": "2021-11-12",
    "latest": "2026-04-24",
    "count": 1115
  },
  "lennar": {
    "earliest": "2021-11-12",
    "latest": "2026-04-24",
    "count": 1115
  },
  "pultegroup": {
    "earliest": "2021-11-12",
    "latest": "2026-04-24",
    "count": 1115
  },
  "toll_brothers": {
    "earliest": "2021-11-12",
    "latest": "2026-04-24",
    "count": 1115
  },
  "kb_home": {
    "earliest": "2021-11-12",
    "latest": "2026-04-24",
    "count": 1115
  },
  "nvr": {
    "earliest": "2021-11-12",
    "latest": "2026-04-24",
    "count": 1115
  },
  "daiwa_house": {
    "earliest": "2021-11-17",
    "latest": "2026-04-24",
    "count": 1085
  },
  "sekisui_house": {
    "earliest": "2021-11-17",
    "latest": "2026-04-24",
    "count": 1085
  },
  "sumitomo_forestry": {
    "earliest": "2021-11-17",
    "latest": "2026-04-24",
    "count": 1085
  },
  "etf_vnq": {
    "earliest": "2021-11-12",
    "latest": "2026-04-24",
    "count": 1115
  },
  "etf_xlre": {
    "earliest": "2021-11-12",
    "latest": "2026-04-24",
    "count": 1115
  },
  "etf_xhb": {
    "earliest": "2021-11-12",
    "latest": "2026-04-24",
    "count": 1115
  },
  "etf_itb": {
    "earliest": "2021-11-12",
    "latest": "2026-04-24",
    "count": 1115
  }
}