{
  "updated_at": "2026-05-16T09:29:12.034483+00:00",
  "companies": {
    "taiwan_cement": {
      "name": "台灣水泥",
      "short_name": "台泥",
      "ticker": "1101.TW",
      "holders": [
        {
          "holder": "VANGUARD STAR FUNDS-Vanguard Total International Stock Index Fund",
          "shares": 95034758,
          "pct_held": 1.26,
          "value": 2290337704
        },
        {
          "holder": "VANGUARD Intl Eqy. INDEX Fd.S-Vanguard Emerging Markets Stock Index Fd",
          "shares": 84916717,
          "pct_held": 1.12,
          "value": 2046492912
        },
        {
          "holder": "iShares, Inc.-iShares Core MSCI Emerging Markets ETF",
          "shares": 62797182,
          "pct_held": 0.83,
          "value": 1513412110
        },
        {
          "holder": "iShares, Inc.-iShares MSCI Taiwan ETF",
          "shares": 41669645,
          "pct_held": 0.55,
          "value": 1004238460
        },
        {
          "holder": "Dimensional Emerging Markets Value Fund",
          "shares": 18560110,
          "pct_held": 0.25,
          "value": 447298658
        },
        {
          "holder": "DFA INVESTMENT DIMENSIONS GROUP INC-Emerging Markets Core Eqy. 2 PORT.",
          "shares": 14251055,
          "pct_held": 0.19,
          "value": 343450430
        },
        {
          "holder": "iShares, Inc.-iShares MSCI Emerging Markets ex China ETF",
          "shares": 14595671,
          "pct_held": 0.19,
          "value": 351755676
        },
        {
          "holder": "iShares, Inc.-iShares MSCI Emerging Markets ETF",
          "shares": 14087748,
          "pct_held": 0.19,
          "value": 339514732
        },
        {
          "holder": "VANGUARD Intl Eqy. INDEX Fd.S-Vanguard FTSE All-World ex-US Index Fd.",
          "shares": 13769726,
          "pct_held": 0.18,
          "value": 331850401
        },
        {
          "holder": "Fidelity Salem Street Trust-Fidelity Series Global ex U.S. Index Fund",
          "shares": 12265302,
          "pct_held": 0.16,
          "value": 295593782
        }
      ]
    },
    "nippon_steel": {
      "name": "日本製鐵",
      "short_name": "新日鐵",
      "ticker": "5401.T",
      "holders": [
        {
          "holder": "Pacer Advisors, Inc.",
          "shares": 91253,
          "pct_held": 0.01,
          "value": 51092556
        },
        {
          "holder": "Coston, McIsaac & Partners",
          "shares": 360,
          "pct_held": 0.0,
          "value": 201564
        }
      ]
    },
    "crh": {
      "name": "CRH",
      "short_name": "CRH plc",
      "ticker": "CRH",
      "holders": [
        {
          "holder": "Blackrock Inc.",
          "shares": 52230347,
          "pct_held": 7.82,
          "value": 5390694066
        },
        {
          "holder": "Vanguard Capital Management LLC",
          "shares": 43477329,
          "pct_held": 6.51,
          "value": 4487295086
        },
        {
          "holder": "FMR, LLC",
          "shares": 40215860,
          "pct_held": 6.02,
          "value": 4150678873
        },
        {
          "holder": "Vanguard Portfolio Management LLC",
          "shares": 32090966,
          "pct_held": 4.8,
          "value": 3312108571
        },
        {
          "holder": "State Street Corporation",
          "shares": 24895205,
          "pct_held": 3.73,
          "value": 2569434085
        },
        {
          "holder": "Geode Capital Management, LLC",
          "shares": 14709575,
          "pct_held": 2.2,
          "value": 1518175222
        },
        {
          "holder": "Franklin Resources, Inc.",
          "shares": 14566259,
          "pct_held": 2.18,
          "value": 1503383578
        },
        {
          "holder": "Massachusetts Financial Services Co.",
          "shares": 13507797,
          "pct_held": 2.02,
          "value": 1394139716
        },
        {
          "holder": "Dz Bank Ag Deutsche Zentral Genossenschafts Bank, Frankfurt Am Main",
          "shares": 12877115,
          "pct_held": 1.93,
          "value": 1329047027
        },
        {
          "holder": "Royal Bank of Canada",
          "shares": 10808439,
          "pct_held": 1.62,
          "value": 1115538979
        }
      ]
    },
    "vulcan_materials": {
      "name": "Vulcan Materials",
      "short_name": "Vulcan",
      "ticker": "VMC",
      "holders": [
        {
          "holder": "Blackrock Inc.",
          "shares": 9962802,
          "pct_held": 7.68,
          "value": 2668337125
        },
        {
          "holder": "State Farm Mutual Automobile Insurance Co",
          "shares": 9521730,
          "pct_held": 7.34,
          "value": 2550204818
        },
        {
          "holder": "Vanguard Capital Management LLC",
          "shares": 8532407,
          "pct_held": 6.58,
          "value": 2285234452
        },
        {
          "holder": "Vanguard Portfolio Management LLC",
          "shares": 7030649,
          "pct_held": 5.42,
          "value": 1883018627
        },
        {
          "holder": "Principal Financial Group, Inc.",
          "shares": 6642386,
          "pct_held": 5.12,
          "value": 1779030153
        },
        {
          "holder": "JPMORGAN CHASE & CO",
          "shares": 5769350,
          "pct_held": 4.45,
          "value": 1545204933
        },
        {
          "holder": "State Street Corporation",
          "shares": 5472987,
          "pct_held": 4.22,
          "value": 1465830034
        },
        {
          "holder": "FMR, LLC",
          "shares": 4464350,
          "pct_held": 3.44,
          "value": 1195686800
        },
        {
          "holder": "Geode Capital Management, LLC",
          "shares": 3576172,
          "pct_held": 2.76,
          "value": 957806098
        },
        {
          "holder": "ClearBridge Investments, LLC",
          "shares": 2326275,
          "pct_held": 1.79,
          "value": 623046202
        }
      ]
    },
    "caterpillar": {
      "name": "Caterpillar",
      "short_name": "卡特彼勒",
      "ticker": "CAT",
      "holders": [
        {
          "holder": "Blackrock Inc.",
          "shares": 37169433,
          "pct_held": 8.07,
          "value": 33017978937
        },
        {
          "holder": "State Street Corporation",
          "shares": 35388550,
          "pct_held": 7.68,
          "value": 31436002764
        },
        {
          "holder": "Vanguard Capital Management LLC",
          "shares": 30234453,
          "pct_held": 6.56,
          "value": 26857566870
        },
        {
          "holder": "State Farm Mutual Automobile Insurance Co",
          "shares": 14564726,
          "pct_held": 3.16,
          "value": 12937991717
        },
        {
          "holder": "Vanguard Portfolio Management LLC",
          "shares": 11705890,
          "pct_held": 2.54,
          "value": 10398459117
        },
        {
          "holder": "Geode Capital Management, LLC",
          "shares": 10610182,
          "pct_held": 2.3,
          "value": 9425130746
        },
        {
          "holder": "Fisher Asset Management, LLC",
          "shares": 9775952,
          "pct_held": 2.12,
          "value": 8684075897
        },
        {
          "holder": "Morgan Stanley",
          "shares": 7075119,
          "pct_held": 1.54,
          "value": 6284898941
        },
        {
          "holder": "Bank of America Corporation",
          "shares": 6738802,
          "pct_held": 1.46,
          "value": 5986145188
        },
        {
          "holder": "Gates Foundation Trust",
          "shares": 6353614,
          "pct_held": 1.38,
          "value": 5643978836
        }
      ]
    },
    "saint_gobain": {
      "name": "Saint-Gobain",
      "short_name": "聖戈班",
      "ticker": "SGO.PA",
      "holders": [
        {
          "holder": "Pacer Advisors, Inc.",
          "shares": 9648,
          "pct_held": 0.0,
          "value": 718004
        },
        {
          "holder": "Paradigm Asset Management Company, LLC",
          "shares": 22900,
          "pct_held": 0.0,
          "value": 1704217
        }
      ]
    },
    "dr_horton": {
      "name": "D.R. Horton",
      "short_name": "DR Horton",
      "ticker": "DHI",
      "holders": [
        {
          "holder": "Capital World Investors",
          "shares": 36936106,
          "pct_held": 13.02,
          "value": 5000779368
        },
        {
          "holder": "Blackrock Inc.",
          "shares": 27843232,
          "pct_held": 9.82,
          "value": 3769695163
        },
        {
          "holder": "Vanguard Capital Management LLC",
          "shares": 17221229,
          "pct_held": 6.07,
          "value": 2331582183
        },
        {
          "holder": "Vanguard Portfolio Management LLC",
          "shares": 12566502,
          "pct_held": 4.43,
          "value": 1701378698
        },
        {
          "holder": "State Street Corporation",
          "shares": 12092080,
          "pct_held": 4.26,
          "value": 1637146703
        },
        {
          "holder": "FMR, LLC",
          "shares": 7426660,
          "pct_held": 2.62,
          "value": 1005495492
        },
        {
          "holder": "Geode Capital Management, LLC",
          "shares": 7191534,
          "pct_held": 2.54,
          "value": 973661783
        },
        {
          "holder": "JPMORGAN CHASE & CO",
          "shares": 4795057,
          "pct_held": 1.69,
          "value": 649202764
        },
        {
          "holder": "Capital Research Global Investors",
          "shares": 4657746,
          "pct_held": 1.64,
          "value": 630612228
        },
        {
          "holder": "Morgan Stanley",
          "shares": 3684724,
          "pct_held": 1.3,
          "value": 498874780
        }
      ]
    },
    "lennar": {
      "name": "Lennar",
      "short_name": "Lennar",
      "ticker": "LEN",
      "holders": [
        {
          "holder": "Blackrock Inc.",
          "shares": 18256480,
          "pct_held": 8.46,
          "value": 1502508359
        },
        {
          "holder": "Vanguard Capital Management LLC",
          "shares": 12947306,
          "pct_held": 6.0,
          "value": 1065563323
        },
        {
          "holder": "Eagle Capital Management LLC",
          "shares": 10986212,
          "pct_held": 5.09,
          "value": 904165281
        },
        {
          "holder": "Greenhaven Associates, Inc.",
          "shares": 10632131,
          "pct_held": 4.93,
          "value": 875024413
        },
        {
          "holder": "State Street Corporation",
          "shares": 10104819,
          "pct_held": 4.68,
          "value": 831626634
        },
        {
          "holder": "Vanguard Portfolio Management LLC",
          "shares": 9526409,
          "pct_held": 4.42,
          "value": 784023489
        },
        {
          "holder": "Aristotle Capital Management, LLC",
          "shares": 8725950,
          "pct_held": 4.04,
          "value": 718145711
        },
        {
          "holder": "Berkshire Hathaway, Inc",
          "shares": 7050950,
          "pct_held": 3.27,
          "value": 580293206
        },
        {
          "holder": "Manufacturers Life Insurance Co.",
          "shares": 6089621,
          "pct_held": 2.82,
          "value": 501175826
        },
        {
          "holder": "Geode Capital Management, LLC",
          "shares": 5621682,
          "pct_held": 2.61,
          "value": 462664445
        }
      ]
    },
    "pultegroup": {
      "name": "PulteGroup",
      "short_name": "Pulte",
      "ticker": "PHM",
      "holders": [
        {
          "holder": "Blackrock Inc.",
          "shares": 19256894,
          "pct_held": 10.11,
          "value": 2120376610
        },
        {
          "holder": "Franklin Resources, Inc.",
          "shares": 14978904,
          "pct_held": 7.86,
          "value": 1649327128
        },
        {
          "holder": "Vanguard Capital Management LLC",
          "shares": 12506660,
          "pct_held": 6.57,
          "value": 1377108340
        },
        {
          "holder": "State Street Corporation",
          "shares": 9115122,
          "pct_held": 4.79,
          "value": 1003666088
        },
        {
          "holder": "Vanguard Portfolio Management LLC",
          "shares": 8178323,
          "pct_held": 4.29,
          "value": 900515150
        },
        {
          "holder": "FMR, LLC",
          "shares": 6561037,
          "pct_held": 3.44,
          "value": 722435788
        },
        {
          "holder": "Greenhaven Associates, Inc.",
          "shares": 5497109,
          "pct_held": 2.89,
          "value": 605286675
        },
        {
          "holder": "Geode Capital Management, LLC",
          "shares": 5210744,
          "pct_held": 2.74,
          "value": 573755025
        },
        {
          "holder": "First Trust Advisors LP",
          "shares": 4314501,
          "pct_held": 2.26,
          "value": 475069707
        },
        {
          "holder": "Price (T.Rowe) Associates Inc",
          "shares": 4284197,
          "pct_held": 2.25,
          "value": 471732934
        }
      ]
    },
    "toll_brothers": {
      "name": "Toll Brothers",
      "short_name": "Toll Brothers",
      "ticker": "TOL",
      "holders": [
        {
          "holder": "Blackrock Inc.",
          "shares": 9949088,
          "pct_held": 10.51,
          "value": 1255773899
        },
        {
          "holder": "Greenhaven Associates, Inc.",
          "shares": 5645309,
          "pct_held": 5.96,
          "value": 712550908
        },
        {
          "holder": "Capital World Investors",
          "shares": 5207777,
          "pct_held": 5.5,
          "value": 657325619
        },
        {
          "holder": "Vanguard Capital Management LLC",
          "shares": 4252652,
          "pct_held": 4.49,
          "value": 536769740
        },
        {
          "holder": "Vanguard Portfolio Management LLC",
          "shares": 4170253,
          "pct_held": 4.4,
          "value": 526369338
        },
        {
          "holder": "State Street Corporation",
          "shares": 3370846,
          "pct_held": 3.56,
          "value": 425468186
        },
        {
          "holder": "FMR, LLC",
          "shares": 3312902,
          "pct_held": 3.5,
          "value": 418154494
        },
        {
          "holder": "Price (T.Rowe) Associates Inc",
          "shares": 3303915,
          "pct_held": 3.49,
          "value": 417020155
        },
        {
          "holder": "Dimensional Fund Advisors LP",
          "shares": 2990447,
          "pct_held": 3.16,
          "value": 377454223
        },
        {
          "holder": "Geode Capital Management, LLC",
          "shares": 2307242,
          "pct_held": 2.44,
          "value": 291220088
        }
      ]
    },
    "kb_home": {
      "name": "KB Home",
      "short_name": "KB Home",
      "ticker": "KBH",
      "holders": [
        {
          "holder": "Blackrock Inc.",
          "shares": 9382121,
          "pct_held": 14.98,
          "value": 422852190
        },
        {
          "holder": "FMR, LLC",
          "shares": 5648971,
          "pct_held": 9.02,
          "value": 254599121
        },
        {
          "holder": "State Street Corporation",
          "shares": 3260136,
          "pct_held": 5.2,
          "value": 146934328
        },
        {
          "holder": "Capital World Investors",
          "shares": 2957918,
          "pct_held": 4.72,
          "value": 133313363
        },
        {
          "holder": "Vanguard Portfolio Management LLC",
          "shares": 2903154,
          "pct_held": 4.63,
          "value": 130845149
        },
        {
          "holder": "Vanguard Capital Management LLC",
          "shares": 2509809,
          "pct_held": 4.01,
          "value": 113117090
        },
        {
          "holder": "Dimensional Fund Advisors LP",
          "shares": 2310462,
          "pct_held": 3.69,
          "value": 104132521
        },
        {
          "holder": "Geode Capital Management, LLC",
          "shares": 1594352,
          "pct_held": 2.54,
          "value": 71857444
        },
        {
          "holder": "Nomura Asset Management International Inc",
          "shares": 1548707,
          "pct_held": 2.47,
          "value": 69800224
        },
        {
          "holder": "Invesco Ltd.",
          "shares": 1275458,
          "pct_held": 2.04,
          "value": 57484891
        }
      ]
    },
    "nvr": {
      "name": "NVR",
      "short_name": "NVR Inc",
      "ticker": "NVR",
      "holders": [
        {
          "holder": "Blackrock Inc.",
          "shares": 281955,
          "pct_held": 10.45,
          "value": 1568690510
        },
        {
          "holder": "Vanguard Capital Management LLC",
          "shares": 177625,
          "pct_held": 6.58,
          "value": 988238023
        },
        {
          "holder": "Capital Research Global Investors",
          "shares": 162965,
          "pct_held": 6.04,
          "value": 906675352
        },
        {
          "holder": "State Street Corporation",
          "shares": 129430,
          "pct_held": 4.79,
          "value": 720099351
        },
        {
          "holder": "Vanguard Portfolio Management LLC",
          "shares": 119297,
          "pct_held": 4.42,
          "value": 663723189
        },
        {
          "holder": "Geode Capital Management, LLC",
          "shares": 75268,
          "pct_held": 2.79,
          "value": 418762558
        },
        {
          "holder": "Principal Financial Group, Inc.",
          "shares": 58245,
          "pct_held": 2.16,
          "value": 324053053
        },
        {
          "holder": "Boston Partners",
          "shares": 57983,
          "pct_held": 2.15,
          "value": 322595385
        },
        {
          "holder": "Invesco Ltd.",
          "shares": 42997,
          "pct_held": 1.59,
          "value": 239218974
        },
        {
          "holder": "Capital World Investors",
          "shares": 40761,
          "pct_held": 1.51,
          "value": 226778719
        }
      ]
    },
    "daiwa_house": {
      "name": "大和房屋",
      "short_name": "大和房屋",
      "ticker": "1925.T",
      "holders": [
        {
          "holder": "Paradigm Asset Management Company, LLC",
          "shares": 48000,
          "pct_held": 0.01,
          "value": 217824000
        },
        {
          "holder": "Pacer Advisors, Inc.",
          "shares": 4909,
          "pct_held": 0.0,
          "value": 22277042
        }
      ]
    },
    "sekisui_house": {
      "name": "積水房屋",
      "short_name": "積水房屋",
      "ticker": "1928.T",
      "holders": [
        {
          "holder": "Pacer Advisors, Inc.",
          "shares": 5355,
          "pct_held": 0.0,
          "value": 18185580
        },
        {
          "holder": "Heritage Wealth Advisors",
          "shares": 806,
          "pct_held": 0.0,
          "value": 2737176
        }
      ]
    },
    "sumitomo_forestry": {
      "name": "住友林業",
      "short_name": "住友林業",
      "ticker": "1911.T",
      "holders": [
        {
          "holder": "Pacer Advisors, Inc.",
          "shares": 47448,
          "pct_held": 0.02,
          "value": 61468884
        }
      ]
    }
  }
}